COS/Assignment2/encoder8to3.v
// Author: Divyansh Mishra and Narayan Jat
// Submission Date: 7 February 2024
// Updation Date: 25 Feb 2024

module encoder8to3 (i, o);
    input [0:7] i;
    output [0:2]o;

    wire [0:7]w;

    assign w[1] = (~i[0] & i[1] & ~i[2] & ~i[3] & ~i[4] & ~i[5] & ~i[6] & ~i[7]);
    assign w[2] = (~i[0] & ~i[1] & i[2] & ~i[3] & ~i[4] & ~i[5] & ~i[6] & ~i[7]);
    assign w[3] = (~i[0] & ~i[1] & ~i[2] & i[3] & ~i[4] & ~i[5] & ~i[6] & ~i[7]);
    assign w[4] = (~i[0] & ~i[1] & ~i[2] & ~i[3] & i[4] & ~i[5] & ~i[6] & ~i[7]);
    assign w[5] = (~i[0] & ~i[1] & ~i[2] & ~i[3] & ~i[4] & i[5] & ~i[6] & ~i[7]);
    assign w[6] = (~i[0] & ~i[1] & ~i[2] & ~i[3] & ~i[4] & ~i[5] & i[6] & ~i[7]);
    assign w[7] = (~i[0] & ~i[1] & ~i[2] & ~i[3] & ~i[4] & ~i[5] & ~i[6] & i[7]);
    
    assign o[0] = w[7] | w[5] | w[3] | w[1];
    assign o[1] = w[7] | w[6] | w[3] | w[2];
    assign o[2] = w[7] | w[6] | w[5] | w[4];

endmodule

COS/Assignment2/tb_encoder.v
// Author: Divyansh Mishra and Narayan Jat
// Submission Date: 7 February 2024
// Updation Date: 25 Feb 2024

`include "encoder8to3.v"

module tb_encoder8to3;
reg [0:7]i;
wire [0:2]o;

encoder8to3 f1(i, o);

initial begin
    $monitor("input=%b, output=%b\n", i, o);
    #2 i=8'b10000000;
    #2 i=8'b01000000;
    #2 i=8'b00100000;
    #2 i=8'b00010000;
    #2 i=8'b00001000;
    #2 i=8'b00000100;
    #2 i=8'b00000010;
    #2 i=8'b00000001;
end

initial begin
 $dumpfile("out.vcd");
 $dumpvars;
 #100 $finish;
end

endmodule

COS/Assignment2/out.vcd
$date
	Tue Feb 27 23:24:19 2024
$end
$version
	Icarus Verilog
$end
$timescale
	1s
$end
$scope module tb_encoder8to3 $end
$var wire 3 ! o [0:2] $end
$var reg 8 " i [0:7] $end
$scope module f1 $end
$var wire 8 # i [0:7] $end
$var wire 8 $ w [0:7] $end
$var wire 3 % o [0:2] $end
$upscope $end
$upscope $end
$enddefinitions $end
#0
$dumpvars
bx %
bzxxxxxxx $
bx #
bx "
bx !
$end
#2
b0 !
b0 %
bz0000000 $
b10000000 "
b10000000 #
#4
b100 !
b100 %
bz1000000 $
b1000000 "
b1000000 #
#6
b10 !
b10 %
bz0100000 $
b100000 "
b100000 #
#8
b110 !
b110 %
bz0010000 $
b10000 "
b10000 #
#10
b1 !
b1 %
bz0001000 $
b1000 "
b1000 #
#12
b101 !
b101 %
bz0000100 $
b100 "
b100 #
#14
b11 !
b11 %
bz0000010 $
b10 "
b10 #
#16
b111 !
b111 %
bz0000001 $
b1 "
b1 #
